mx_requests.py
mx_requests-0.1.1.dist-info/LICENSE
mx_requests-0.1.1.dist-info/METADATA
mx_requests-0.1.1.dist-info/WHEEL
mx_requests-0.1.1.dist-info/top_level.txt
mx_requests-0.1.1.dist-info/RECORD
