Metadata-Version: 2.1
Name: mx_requests
Version: 0.1.1
Summary: Drop-in requests replacement using MontgomeryNX proxy
Author-email: Scott Montgomery <section31nx@users.noreply.github.com>
License: MIT
Project-URL: Homepage, https://www.montgomerynx.com
Project-URL: Source, https://github.com/section31nx/mx_requests
Requires-Python: >=3.7
License-File: LICENSE
Requires-Dist: requests
